MathStuff/__init__.py
MathStuff/calculus.py
MathStuff/fourier_series.py
MathStuff/graph_2d.py
MathStuff/helper.py
MathStuff/logic.py
MathStuff/main.py
MathStuff/taylor_series.py
MathStuff-0.0.3.dist-info/LICENSE.md
MathStuff-0.0.3.dist-info/METADATA
MathStuff-0.0.3.dist-info/WHEEL
MathStuff-0.0.3.dist-info/top_level.txt
MathStuff-0.0.3.dist-info/RECORD
