Metadata-Version: 2.1
Name: MathStuff
Version: 0.0.3
Summary: Math Stuff
Home-page: https://github.com/Vipul-Cariappa/Math-Stuff
Author: Vipul Cariappa
Author-email: Vipul Cariappa <vipulcariappa@gmail.com>
License: MIT
Project-URL: Homepage, https://github.com/Vipul-Cariappa/Math-Stuff
Project-URL: Bug Tracker, https://github.com/Vipul-Cariappa/Math-Stuff/issues
Classifier: Programming Language :: Python :: 3
Classifier: License :: OSI Approved :: MIT License
Classifier: Operating System :: OS Independent
Requires-Python: >=3.7
License-File: LICENSE.md
Requires-Dist: matplotlib (==3.6.3)
Requires-Dist: numpy (==1.24.1)
Requires-Dist: sympy (==1.11.1)
